textual_reflect/__init__.py
textual_reflect/__main__.py
textual_reflect/reflect.py
textual_reflect/reflect.tcss
textual_reflect-0.1.7.dist-info/METADATA
textual_reflect-0.1.7.dist-info/WHEEL
textual_reflect-0.1.7.dist-info/licenses/LICENSE
textual_reflect-0.1.7.dist-info/RECORD
