Metadata-Version: 2.4
Name: textual-reflect
Version: 0.1.7
Summary: A Textual widget for code reflection and introspection.
Project-URL: Homepage, https://github.com/Ismael-VC/textual-reflect
Project-URL: Repository, https://github.com/Ismael-VC/textual-reflect.git
Project-URL: Bug Tracker, https://github.com/Ismael-VC/textual-reflect/issues
Author-email: Ismael Venegas Castelló <ismael.vc13337@gmail.com>
License: MIT
License-File: LICENSE
Classifier: License :: OSI Approved :: MIT License
Classifier: Operating System :: OS Independent
Classifier: Programming Language :: Python :: 3
Requires-Python: <4.0,>=3.9
Requires-Dist: textual>=6.4.0
Provides-Extra: dev
Requires-Dist: pytest; extra == 'dev'
Requires-Dist: ruff; extra == 'dev'
Provides-Extra: syntax
Requires-Dist: textual[syntax]>=6.4.0; extra == 'syntax'
